kaartmaker/__init__.py
kaartmaker/config/boundaries.json
kaartmaker/config/country_labels.json
kaartmaker/config/legend.json
kaartmaker/constants.py
kaartmaker/datasets/UNRWA/2017-2023_top_20_rank_total_0.pdf
kaartmaker/datasets/UNRWA/2022-2023_programme_budget_blue_book_-_final_211021_0.pdf
kaartmaker/datasets/UNRWA/source.yaml
kaartmaker/datasets/UNRWA/world_unrwa_funding.csv
kaartmaker/datasets/UN_general_assembly/israel_ceasefire/source.yaml
kaartmaker/datasets/UN_general_assembly/israel_ceasefire/world_palestine_votes.csv
kaartmaker/datasets/UN_general_assembly/russia_ceasefire/resolution_text.pdf
kaartmaker/datasets/UN_general_assembly/russia_ceasefire/source.yml
kaartmaker/datasets/UN_general_assembly/russia_ceasefire/world_ukraine_votes.csv
kaartmaker/geojson/world.geojson
kaartmaker/geojson/world_subunits.geojson
kaartmaker/help_text.py
kaartmaker/labeling.py
kaartmaker/plotly.py
kaartmaker/process_dataset.py
kaartmaker-0.1.6.dist-info/LICENSE
kaartmaker-0.1.6.dist-info/METADATA
kaartmaker-0.1.6.dist-info/WHEEL
kaartmaker-0.1.6.dist-info/entry_points.txt
kaartmaker-0.1.6.dist-info/RECORD
