Metadata-Version: 2.3
Name: kaartmaker
Version: 0.1.6
Summary: world map making tool based on votes from locations such as the UN
License: AGPL-3.0-or-later
Keywords: geopandas,maps,mapmaking,kaartmaker,UN
Author: Jesse Hitch
Author-email: jessebot@linux.com
Requires-Python: >=3.12,<4.0
Classifier: Development Status :: 3 - Alpha
Classifier: Intended Audience :: End Users/Desktop
Classifier: License :: OSI Approved :: GNU Affero General Public License v3 or later (AGPLv3+)
Classifier: Operating System :: MacOS :: MacOS X
Classifier: Operating System :: POSIX :: Linux
Classifier: Programming Language :: Python :: 3
Classifier: Programming Language :: Python :: 3.12
Classifier: Programming Language :: Python :: 3.13
Requires-Dist: click (>=8.1,<9.0)
Requires-Dist: fake-useragent (>=1.5,<2.0)
Requires-Dist: geopandas (>=0.14,<0.15)
Requires-Dist: matplotlib (>=3.8,<4.0)
Requires-Dist: numpy (>=1.26,<2.0)
Requires-Dist: pandas (>=2.2,<3.0)
Requires-Dist: plotly (>=5.22,<6.0)
Requires-Dist: pyqt5-sip (>=12.11,<13.0)
Requires-Dist: rich (>=13.7,<14.0)
Requires-Dist: seaborn (>=0.13,<0.14)
Project-URL: Bug Tracker, http://github.com/small-hack/kaartmaker/issues
